an_condamanager/__init__.py
an_condamanager/condamanager.py
an_condamanager-1.3.11.dist-info/licenses/LICENSE
an_condamanager-1.3.11.dist-info/METADATA
an_condamanager-1.3.11.dist-info/WHEEL
an_condamanager-1.3.11.dist-info/top_level.txt
an_condamanager-1.3.11.dist-info/RECORD
