Metadata-Version: 2.4
Name: an_condamanager
Version: 1.3.11
Summary: A package for an_condamanager.
Home-page: https://github.com/Atsushi888/Atsushi888
Author: Atsushi888
Author-email: Atsushi888 <vtgrotxu@gmail.com>
Project-URL: Homepage, https://github.com/Atsushi888/an_condamanager
Project-URL: Repository, https://github.com/Atsushi888/an_condamanager
Requires-Python: >=3.6
License-File: LICENSE
Requires-Dist: an_DebugHelper>=1.3.3
Requires-Dist: an_CudaUtility
Requires-Dist: an_QuickViper2
Requires-Dist: an_UniqueEnvVar
Requires-Dist: an_EasyVen
Requires-Dist: an_ToolKit
Dynamic: author
Dynamic: home-page
Dynamic: license-file
Dynamic: requires-python
